misc/MotionDetection.py
misc/MotionDetection_EXC.py
misc/MotionDetection_v2.py
misc/__init__.py
misc/debug.py
misc/detection_utils.py
misc/digital_she_config.py
misc/firesmoke_detector.py
misc/firesmoke_detector_v1.py
misc/firesmoke_detector_v2.py
misc/firesmoke_detector_v3.py
misc/firesmoke_detector_v4.py
misc/labelmap_util.py
misc/logging_config.py
misc/logging_handler.py
misc/application_util/__init__.py
misc/application_util/detection_utils.py
misc/application_util/feature_extractor.py
misc/application_util/image_viewer.py
misc/application_util/preprocessing.py
misc/application_util/visualization.py
misc/deep_sort/__init__.py
misc/deep_sort/detection.py
misc/deep_sort/iou_matching.py
misc/deep_sort/kalman_filter.py
misc/deep_sort/linear_assignment.py
misc/deep_sort/nn_matching.py
misc/deep_sort/sklearn_linear_assignment.py
misc/deep_sort/track.py
misc/deep_sort/tracker.py
misc/estimator/__init__.py
misc/estimator/action_estimate.py
misc/estimator/condition_estimate.py
misc/estimator/cqueue.py
misc/loitering/__init__.py
misc/loitering/loitering_tracker.py
misc/loitering/track.py
misc/tools/__init__.py
misc/tools/freeze_model.py
misc/tools/generate_detections.py
misc/tools/string_int_label_map_pb2.py
models/__init__.py
models/basemodel.py
models/classify.py
models/context.py
models/inference_manager.py
models/objectdetect.py
service/__init__.py
service/constants.py
service/digitalshe_service.py
service/va_service.py
vaengine/__init__.py
vaengine/cctv_exc_va.py
vaengine/cluster_va.py
vaengine/crossline_va.py
vaengine/detection_va.py
vaengine/detection_va_v2.py
vaengine/detection_va_v3.py
vaengine/detection_va_v4.py
vaengine/falldown_va.py
vaengine/falldown_va_2.py
vaengine/firesmoke_va.py
vaengine/firesmoke_va_2.py
vaengine/firesmoke_va_3.py
vaengine/firesmoke_va_4.py
vaengine/firesmoke_va_5.py
vaengine/firesmoke_va_6.py
vaengine/harness_va.py
vaengine/harness_va_v2.py
vaengine/helmet_va.py
vaengine/helmet_va_2.py
vaengine/intrusion_va.py
aidenva-0.0.1.dist-info/METADATA
aidenva-0.0.1.dist-info/WHEEL
aidenva-0.0.1.dist-info/top_level.txt
aidenva-0.0.1.dist-info/RECORD
