Metadata-Version: 2.1
Name: aidenva
Version: 0.0.1
Summary: SK C&C
Home-page: https://github.com/digitalshe
Author: skcc vision ai
Author-email: visionai@sk.com
License: UNKNOWN
Platform: UNKNOWN
Classifier: Programming Language :: Python :: 3.7
Requires-Python: >=3.6
